__init__.py
automake.py
builder.py
cmake.py
detect.py
function.py
globa.py
graph.py
log.py
node.py
op.py
toolchain.py
version.py
yaya.py
yymake-0.9.4.dist-info/LICENSE
yymake-0.9.4.dist-info/METADATA
yymake-0.9.4.dist-info/WHEEL
yymake-0.9.4.dist-info/entry_points.txt
yymake-0.9.4.dist-info/top_level.txt
yymake-0.9.4.dist-info/RECORD
