Metadata-Version: 2.1
Name: yymake
Version: 0.9.4
Summary: A cross build dsl make tool
Home-page: https://github.com/evilbinary/ymake
Author: evilbinary
Author-email: rootntsd@gmail.com
Project-URL: Bug Tracker, https://github.com/evilbinary/ymake/issues
Classifier: Programming Language :: Python :: 3
Classifier: License :: OSI Approved :: MIT License
Classifier: Operating System :: OS Independent
Requires-Python: >=2.6
License-File: LICENSE
Requires-Dist: pytest
Requires-Dist: colorama
Requires-Dist: networkx
Requires-Dist: colorlog
Requires-Dist: diskcache
